{
  "items": [
    {
      "attrs": {
        "id": "home",
        "class": "home-menu-item"
      },
      "target": "#home",
      "label": {
        "EN": "POLICY HOME"
      }
    },
    {
      "attrs": {
        "id": "policiesAtAglance"
      },
      "target": "#policiesAtAglance",
      "label": {
        "EN": "POLICIES AT A GLANCE"
      }
    },
    {
      "attrs": {
        "id": "qAd"
      },
      "target": "#queryAnddownloads",
      "label": {
        "EN": "QUERY AND DOWNLOAD"
      }
    },
    {
      "attrs": {
        "id": "resources"
      },
      "target": "#resources",
      "label": {
        "EN": "RESOURCES"
      }
    },
    {
      "attrs": {
        "id": "analysis"
      },
      "target": "#analysis",
      "label": {
        "EN": "DATA MANAGEMENT"
      }
    }
  ],
  "rightItems": [
    {
      "attrs": {
        "id": "login"
      },
      "label": {
        "EN": "LOGIN"
      }
    },
    {
      "attrs": {
        "id": "logout"
      },
      "label": {
        "EN": "LOGOUT"
      }
    },
    {
      "attrs": {
        "id": "login"
      },
      "label": {
        "EN": "AMIS HOME"
      }
    }
  ],
  "type": "static-top"

}